<?xml version = '1.0' encoding = 'UTF-8'?>
<Relation class="oracle.dbtools.crest.model.design.logical.Relation" name="ORDER_USER_ID_FK" directorySegmentName="seg_0" id="1FB2F7B0-1143-F246-48CF-032C3B4CB0AD">
<createdBy>stril</createdBy>
<createdTime>2021-05-26 21:28:11 UTC</createdTime>
<generatorID>2501A287-B8E7-818C-32AD-40390649AE5F</generatorID>
<ownerDesignName>design</ownerDesignName>
<engineerTo>
<item key="84E89687-C7D4-EBE6-0C7A-433729DC2E61" value="true"/>
</engineerTo>
<sourcePk>8D90A299-CD36-7643-870A-6100D98C5E83</sourcePk>
<identifying>false</identifying>
<optionalSource>true</optionalSource>
<optionalTarget>false</optionalTarget>
<sourceCardinality>1</sourceCardinality>
<sourceEntity>630843D1-86E5-8CE8-4FFE-82B8314BA818</sourceEntity>
<targetCardinalityString>*</targetCardinalityString>
<targetEntity>281EAADF-22A4-205F-8420-A78FF8FFEB41</targetEntity>
<transferable>true</transferable>
<deleteRule>NO ACTION</deleteRule>
</Relation>